demos.py
nn_demos.py
sqlearn/__init__.py
sqlearn/linear_regression.py
sqlearn/logistic_regression.py
sqlearn/model_interface.py
sqlearn/sgd_regression.py
sqlearn/nn/__init__.py
sqlearn/nn/core.py
sqlearn/nn/modules.py
square_learn-2.0.0.dist-info/METADATA
square_learn-2.0.0.dist-info/WHEEL
square_learn-2.0.0.dist-info/licenses/LICENSE
square_learn-2.0.0.dist-info/RECORD
