Metadata-Version: 2.1
Name: square-learn
Version: 2.0.0
Summary: A machine learning library in Python
Project-URL: Homepage, https://github.com/idriswardere/square-learn
Author-email: Idris Wardere <iawardere3@gmail.com>, Jeremy Li <lij061703@gmail.com>
License-File: LICENSE
Requires-Python: >=3.7
Requires-Dist: numpy>=1.23.1
Requires-Dist: pandas>=1.4.4
